ai_code_commenter_vraj0703-0.0.4.dist-info/licenses/LICENSE
commenter_tool/__init__.py
commenter_tool/main.py
commenter_tool/data/format.txt
commenter_tool/data/syntax.txt
ai_code_commenter_vraj0703-0.0.4.dist-info/METADATA
ai_code_commenter_vraj0703-0.0.4.dist-info/WHEEL
ai_code_commenter_vraj0703-0.0.4.dist-info/entry_points.txt
ai_code_commenter_vraj0703-0.0.4.dist-info/top_level.txt
ai_code_commenter_vraj0703-0.0.4.dist-info/RECORD
