Metadata-Version: 2.4
Name: ai-code-commenter-vraj0703
Version: 0.0.4
Summary: An AI-powered tool to automatically comment code using local Ollama models.
Author-email: vraj0703 <vraj0703@gmail.com>
License: MIT License
Classifier: Programming Language :: Python :: 3
Classifier: License :: OSI Approved :: MIT License
Classifier: Operating System :: OS Independent
Classifier: Topic :: Software Development :: Documentation
Requires-Python: >=3.8
License-File: LICENSE
Dynamic: license-file
